Metadata-Version: 2.1
Name: scratch3py-wurulin
Version: 0.1.5
Summary: 模拟Scratch，让python像Scarch一样的制作游戏和动画
Author: 吴儒林
Author-email: 946317637@qq.com
